pytorch_calibrated/__init__.py
pytorch_calibrated/configs.py
pytorch_calibrated/data.py
pytorch_calibrated/enums.py
pytorch_calibrated/models.py
pytorch_calibrated/layers/__init__.py
pytorch_calibrated/layers/categorical_calibrator.py
pytorch_calibrated/layers/linear.py
pytorch_calibrated/layers/numerical_calibrator.py
pytorch_calibrated-0.1.1.dist-info/LICENSE
pytorch_calibrated-0.1.1.dist-info/METADATA
pytorch_calibrated-0.1.1.dist-info/WHEEL
pytorch_calibrated-0.1.1.dist-info/top_level.txt
pytorch_calibrated-0.1.1.dist-info/RECORD
