Metadata-Version: 2.1
Name: pytorch-calibrated
Version: 0.1.1
Summary: A PyTorch Library For Interpretable Machine Learning
Author-email: SOTAI <support@sotai.ai>
Maintainer-email: SOTAI <support@sotai.ai>
License: Apache-2.0
Project-URL: Source, https://github.com/SOTAI-Labs/pytorch-calibrated
Project-URL: Documentation, https://github.com/SOTAI-Labs/pytorch-calibrated/tree/dev/docs
Project-URL: Feature Requests, https://github.com/SOTAI-Labs/pytorch-calibrated/issues
Project-URL: Bug Reports, https://github.com/SOTAI-Labs/pytorch-calibrated/issues
Classifier: Development Status :: 3 - Alpha
Classifier: Intended Audience :: Developers
Classifier: Intended Audience :: Science/Research
Classifier: License :: OSI Approved :: Apache Software License
Classifier: Natural Language :: English
Classifier: Programming Language :: Python :: 3 :: Only
Classifier: Programming Language :: Python :: 3.8
Classifier: Programming Language :: Python :: 3.9
Classifier: Programming Language :: Python :: 3.10
Classifier: Topic :: Scientific/Engineering :: Artificial Intelligence
Classifier: Topic :: Software Development :: Libraries :: Python Modules
Requires-Python: <3.11,>=3.8
License-File: LICENSE
Requires-Dist: absl-py (>=1.4.0)
Requires-Dist: graphlib-backport (>=1.0.3)
Requires-Dist: numpy (>=1.23.5)
Requires-Dist: pandas (>=1.5.3)
Requires-Dist: torch (<=2.0.0,>=1.13.1)
